Topsis_Jai_101903156/__init__.py
Topsis_Jai_101903156/topsis.py
Topsis_Jai_101903156-0.1.1.dist-info/LICENSE.txt
Topsis_Jai_101903156-0.1.1.dist-info/METADATA
Topsis_Jai_101903156-0.1.1.dist-info/WHEEL
Topsis_Jai_101903156-0.1.1.dist-info/top_level.txt
Topsis_Jai_101903156-0.1.1.dist-info/RECORD
