Metadata-Version: 2.1
Name: Topsis-Jai-101903156
Version: 0.1.1
Summary: Topsis score calculator
Author: Jai Singh Batth
Author-email: batthjaisingh2000@gmail.com
License: UNKNOWN
Keywords: python,topsis,101903156,JaiSinghBatth
Platform: UNKNOWN
Classifier: Development Status :: 1 - Planning
Classifier: Intended Audience :: Developers
Classifier: Programming Language :: Python :: 3
Classifier: Operating System :: Unix
Classifier: Operating System :: MacOS :: MacOS X
Classifier: Operating System :: Microsoft :: Windows
License-File: LICENSE.txt
